linkedin_pdf_extractor/.DS_Store
linkedin_pdf_extractor/__init__.py
linkedin_pdf_extractor/extractor.py
linkedin_pdf_extractor/skeleton.py
linkedin_pdf_extractor/pdfstructure/__init__.py
linkedin_pdf_extractor/pdfstructure/printer.py
linkedin_pdf_extractor/pdfstructure/source.py
linkedin_pdf_extractor/pdfstructure/utils.py
linkedin_pdf_extractor/pdfstructure/analysis/__init__.py
linkedin_pdf_extractor/pdfstructure/analysis/annotate.py
linkedin_pdf_extractor/pdfstructure/analysis/sizemapper.py
linkedin_pdf_extractor/pdfstructure/analysis/styledistribution.py
linkedin_pdf_extractor/pdfstructure/hierarchy/__init__.py
linkedin_pdf_extractor/pdfstructure/hierarchy/detectheader.py
linkedin_pdf_extractor/pdfstructure/hierarchy/headercompare.py
linkedin_pdf_extractor/pdfstructure/hierarchy/parser.py
linkedin_pdf_extractor/pdfstructure/hierarchy/traversal.py
linkedin_pdf_extractor/pdfstructure/model/__init__.py
linkedin_pdf_extractor/pdfstructure/model/document.py
linkedin_pdf_extractor/pdfstructure/model/style.py
linkedinpdfextractor-1.3.0.dist-info/LICENSE.txt
linkedinpdfextractor-1.3.0.dist-info/METADATA
linkedinpdfextractor-1.3.0.dist-info/WHEEL
linkedinpdfextractor-1.3.0.dist-info/top_level.txt
linkedinpdfextractor-1.3.0.dist-info/RECORD
