Metadata-Version: 2.1
Name: linkedinpdfextractor
Version: 1.3.0
Summary: Add a short description here!
Home-page: https://github.com/pyscaffold/pyscaffold/
Author: Ketan Prabhu
Author-email: ketan.prabhu@gigvistas.com
License: MIT
Project-URL: Documentation, https://pyscaffold.org/
Platform: any
Classifier: Development Status :: 4 - Beta
Classifier: Programming Language :: Python
Requires-Python: >=3.8
License-File: LICENSE.txt
Requires-Dist: sortedcontainers (==2.2.2)
Requires-Dist: pdfminer.six (==20200517)
Requires-Dist: pandas
Requires-Dist: typing
Provides-Extra: testing
Requires-Dist: setuptools ; extra == 'testing'
Requires-Dist: pytest ; extra == 'testing'
Requires-Dist: pytest-cov ; extra == 'testing'
